pytorch_bolt/__init__.py
pytorch_bolt/datamodule/__init__.py
pytorch_bolt/datamodule/base_datamodule.py
pytorch_bolt/datamodule/datamodule.py
pytorch_bolt/loggers/__init__.py
pytorch_bolt/loggers/base_loggers.py
pytorch_bolt/loggers/loggers.py
pytorch_bolt/module/__init__.py
pytorch_bolt/module/module.py
pytorch_bolt/trainer/__init__.py
pytorch_bolt/trainer/base_trainer.py
pytorch_bolt/trainer/trainer.py
PyTorch_Bolt-0.0.2.dist-info/LICENSE
PyTorch_Bolt-0.0.2.dist-info/METADATA
PyTorch_Bolt-0.0.2.dist-info/WHEEL
PyTorch_Bolt-0.0.2.dist-info/top_level.txt
PyTorch_Bolt-0.0.2.dist-info/RECORD
