Metadata-Version: 2.1
Name: PyTorch-Bolt
Version: 0.0.2
Summary: A simple PyTorch wrapper making multi-node multi-GPU training much easier on Slurm
Home-page: https://github.com/yzhang-dev/PyTorch-Bolt
Author: Yi Zhang
Author-email: yizhang.dev@gmail.com
License: MIT
Download-URL: https://github.com/yzhang-dev/PyTorch-Bolt
Keywords: pytorch,pytorch-template,ddp,distributed,slurm
Platform: UNKNOWN
Classifier: License :: OSI Approved :: MIT License
Classifier: Operating System :: OS Independent
Classifier: Programming Language :: Python :: 3
Classifier: Programming Language :: Python :: 3.8
Requires-Python: >=3.8
Requires-Dist: torch (==1.8.1)
Requires-Dist: torchvision (==0.9.1)
Requires-Dist: tensorboard (==2.4.1)
